conlay/__init__.py
conlay/main.py
conlay-1.1.0.dist-info/LICENSE
conlay-1.1.0.dist-info/METADATA
conlay-1.1.0.dist-info/WHEEL
conlay-1.1.0.dist-info/top_level.txt
conlay-1.1.0.dist-info/RECORD
